markdocs/__init__.py
markdocs/cli.py
markdocs-0.0.0.dist-info/entry_points.txt
markdocs-0.0.0.dist-info/LICENSE
markdocs-0.0.0.dist-info/WHEEL
markdocs-0.0.0.dist-info/METADATA
markdocs-0.0.0.dist-info/RECORD
