Metadata-Version: 1.2
Name: markdocs
Version: 0.0.0
Summary: Markdocs - Python documentation using markdown
Home-page: https://github.com/rochacbruno/markdocs
License: UNKNOWN
Author: Bruno Rocha
Author-email: rochacbruno@gmail.com
Maintainer: rochacbruno
Maintainer-email: rochacbruno@gmail.com
Requires-Python: >=3.6
Classifier: Programming Language :: Python :: 3.6
Classifier: Intended Audience :: Developers
Classifier: License :: OSI Approved :: MIT License
Classifier: Topic :: Documentation
Classifier: Topic :: Software Development :: Documentation
Classifier: Topic :: Software Development :: Quality Assurance
Requires-Dist: mistune
